assignment_3/sram_inout/testbench/sram.v
module sram(data, readWrite, enable, address);
	inout [7:0] data;

	input readWrite, enable;
	input [10:0] address;
	
	reg [2047:0] sramReg [7:0];
	
	// readWrite = 1'b1 read, readWrite = 1'b0 write
	assign data = enable? (readWrite? sramReg[address]: data) : 8'bzzzzzzzz;

	always @(address, enable, readWrite) begin
		if (~readWrite & enable) begin	
			sramReg[address] <= data;
		end
	end
endmodule

assignment_3/sram_inout/testbench/sramTop.v
`include "sram.v"

module testBench;
	// connect the two modules
	wire [7:0] data;
	wire readWrite, enable;
	wire [10:0]	address;
	
	sram sram1(data, readWrite, enable, address);
	Tester tester1 (readWrite, enable, address, data);

	initial
	begin
		$dumpfile("sram.vcd");
		$dumpvars(1, sram1);
	end
endmodule

module Tester (readWrite, enable, address, data); 
	
	output readWrite, enable;
	output [10:0]	address; 
	inout [7:0]	data;
	
	reg readWrite, enable;
	reg [10:0]	address;
	reg [7:0]	data1;
	wire [7:0]	data;

	parameter stimDelay = 20;
	integer i;

	assign data = enable? data1 : 8'bzzzzzzzz;
	initial // Response
	begin
		enable = 1'b0;
		address = 8'b0;
		data1 = 11'b0;
		readWrite = 1'b0;
	end
	
	initial // Stimulus
	begin 
	enable = 1'b1; readWrite = 1'b0;
	#stimDelay;
	
	for(i = 0; i < 128; i = i + 1) begin
		#stimDelay; data1 = i; address = i;#stimDelay;
	end
	
	#stimDelay; enable = 1'b1; readWrite = 1'b1;#stimDelay;
	
	for(i = 0; i < 128; i = i + 1) begin
		#stimDelay; address = i;#stimDelay;
	end
	
	$finish; // finish simulation
	end
endmodule

assignment_3/sram_inout/testbench/sram.vcd
$date
	Thu Feb 11 21:04:24 2016
$end
$version
	Icarus Verilog
$end
$timescale
	1s
$end
$scope module testBench $end
$scope module sram1 $end
$var wire 8 ! data [7:0] $end
$var wire 1 " readWrite $end
$var wire 1 # enable $end
$var wire 11 $ address [10:0] $end
$upscope $end
$upscope $end
$enddefinitions $end
#0
$dumpvars
b0 $
1#
0"
bx !
$end
#80
b1 $
#120
b10 $
#160
b11 $
#200
b100 $
#240
b101 $
#280
b110 $
#320
b111 $
#360
b1000 $
#400
b1001 $
#440
b1010 $
#480
b1011 $
#520
b1100 $
#560
b1101 $
#600
b1110 $
#640
b1111 $
#680
b10000 $
#720
b10001 $
#760
b10010 $
#800
b10011 $
#840
b10100 $
#880
b10101 $
#920
b10110 $
#960
b10111 $
#1000
b11000 $
#1040
b11001 $
#1080
b11010 $
#1120
b11011 $
#1160
b11100 $
#1200
b11101 $
#1240
b11110 $
#1280
b11111 $
#1320
b100000 $
#1360
b100001 $
#1400
b100010 $
#1440
b100011 $
#1480
b100100 $
#1520
b100101 $
#1560
b100110 $
#1600
b100111 $
#1640
b101000 $
#1680
b101001 $
#1720
b101010 $
#1760
b101011 $
#1800
b101100 $
#1840
b101101 $
#1880
b101110 $
#1920
b101111 $
#1960
b110000 $
#2000
b110001 $
#2040
b110010 $
#2080
b110011 $
#2120
b110100 $
#2160
b110101 $
#2200
b110110 $
#2240
b110111 $
#2280
b111000 $
#2320
b111001 $
#2360
b111010 $
#2400
b111011 $
#2440
b111100 $
#2480
b111101 $
#2520
b111110 $
#2560
b111111 $
#2600
b1000000 $
#2640
b1000001 $
#2680
b1000010 $
#2720
b1000011 $
#2760
b1000100 $
#2800
b1000101 $
#2840
b1000110 $
#2880
b1000111 $
#2920
b1001000 $
#2960
b1001001 $
#3000
b1001010 $
#3040
b1001011 $
#3080
b1001100 $
#3120
b1001101 $
#3160
b1001110 $
#3200
b1001111 $
#3240
b1010000 $
#3280
b1010001 $
#3320
b1010010 $
#3360
b1010011 $
#3400
b1010100 $
#3440
b1010101 $
#3480
b1010110 $
#3520
b1010111 $
#3560
b1011000 $
#3600
b1011001 $
#3640
b1011010 $
#3680
b1011011 $
#3720
b1011100 $
#3760
b1011101 $
#3800
b1011110 $
#3840
b1011111 $
#3880
b1100000 $
#3920
b1100001 $
#3960
b1100010 $
#4000
b1100011 $
#4040
b1100100 $
#4080
b1100101 $
#4120
b1100110 $
#4160
b1100111 $
#4200
b1101000 $
#4240
b1101001 $
#4280
b1101010 $
#4320
b1101011 $
#4360
b1101100 $
#4400
b1101101 $
#4440
b1101110 $
#4480
b1101111 $
#4520
b1110000 $
#4560
b1110001 $
#4600
b1110010 $
#4640
b1110011 $
#4680
b1110100 $
#4720
b1110101 $
#4760
b1110110 $
#4800
b1110111 $
#4840
b1111000 $
#4880
b1111001 $
#4920
b1111010 $
#4960
b1111011 $
#5000
b1111100 $
#5040
b1111101 $
#5080
b1111110 $
#5120
b1111111 $
#5160
1"
#5200
b0 $
#5240
b1 $
#5280
b10 $
#5320
b11 $
#5360
b100 $
#5400
b101 $
#5440
b110 $
#5480
b111 $
#5520
b1000 $
#5560
b1001 $
#5600
b1010 $
#5640
b1011 $
#5680
b1100 $
#5720
b1101 $
#5760
b1110 $
#5800
b1111 $
#5840
b10000 $
#5880
b10001 $
#5920
b10010 $
#5960
b10011 $
#6000
b10100 $
#6040
b10101 $
#6080
b10110 $
#6120
b10111 $
#6160
b11000 $
#6200
b11001 $
#6240
b11010 $
#6280
b11011 $
#6320
b11100 $
#6360
b11101 $
#6400
b11110 $
#6440
b11111 $
#6480
b100000 $
#6520
b100001 $
#6560
b100010 $
#6600
b100011 $
#6640
b100100 $
#6680
b100101 $
#6720
b100110 $
#6760
b100111 $
#6800
b101000 $
#6840
b101001 $
#6880
b101010 $
#6920
b101011 $
#6960
b101100 $
#7000
b101101 $
#7040
b101110 $
#7080
b101111 $
#7120
b110000 $
#7160
b110001 $
#7200
b110010 $
#7240
b110011 $
#7280
b110100 $
#7320
b110101 $
#7360
b110110 $
#7400
b110111 $
#7440
b111000 $
#7480
b111001 $
#7520
b111010 $
#7560
b111011 $
#7600
b111100 $
#7640
b111101 $
#7680
b111110 $
#7720
b111111 $
#7760
b1000000 $
#7800
b1000001 $
#7840
b1000010 $
#7880
b1000011 $
#7920
b1000100 $
#7960
b1000101 $
#8000
b1000110 $
#8040
b1000111 $
#8080
b1001000 $
#8120
b1001001 $
#8160
b1001010 $
#8200
b1001011 $
#8240
b1001100 $
#8280
b1001101 $
#8320
b1001110 $
#8360
b1001111 $
#8400
b1010000 $
#8440
b1010001 $
#8480
b1010010 $
#8520
b1010011 $
#8560
b1010100 $
#8600
b1010101 $
#8640
b1010110 $
#8680
b1010111 $
#8720
b1011000 $
#8760
b1011001 $
#8800
b1011010 $
#8840
b1011011 $
#8880
b1011100 $
#8920
b1011101 $
#8960
b1011110 $
#9000
b1011111 $
#9040
b1100000 $
#9080
b1100001 $
#9120
b1100010 $
#9160
b1100011 $
#9200
b1100100 $
#9240
b1100101 $
#9280
b1100110 $
#9320
b1100111 $
#9360
b1101000 $
#9400
b1101001 $
#9440
b1101010 $
#9480
b1101011 $
#9520
b1101100 $
#9560
b1101101 $
#9600
b1101110 $
#9640
b1101111 $
#9680
b1110000 $
#9720
b1110001 $
#9760
b1110010 $
#9800
b1110011 $
#9840
b1110100 $
#9880
b1110101 $
#9920
b1110110 $
#9960
b1110111 $
#10000
b1111000 $
#10040
b1111001 $
#10080
b1111010 $
#10120
b1111011 $
#10160
b1111100 $
#10200
b1111101 $
#10240
b1111110 $
#10280
b1111111 $
