assignment_3/sram/testbench/sram.sv
module sram(clock, dataIn, dataOut, readWrite, enable, address);
	input clock;
	input [7:0] dataIn;
	output [7:0] dataOut;

	input readWrite, enable;
	input [10:0] address;
	
	reg [2047:0] sramReg [7:0];
	

	integer i;
	initial begin
		for(i = 0; i < 130; i = i + 1)
			sramReg[i] = 8'b0;
	end
	
	
	assign dataOut = (readWrite & enable)? sramReg[address] : 8'bzzzzzzzz;
	
	always @(posedge clock) begin
		if (~readWrite & enable) begin	
			sramReg[address] <= dataIn;
		end
	end
endmodule

assignment_3/sram/testbench/sramTop.v

`include "sram.sv"

module testBench;
	// connect the two modules
	wire [7:0] dataIn, dataOut;
	wire 		readWrite, enable;
	wire [10:0]	address;
	wire clock;
	
	sram sram1(clock, dataIn, dataOut, readWrite, enable, address);
	Tester tester1 (clock, readWrite, enable, address, dataIn, dataOut);

	initial
	begin
		$dumpfile("sram.vcd");
		$dumpvars(1, sram1);
	end
endmodule

module Tester (clock, readWrite, enable, address, dataIn, dataOut); 
	output clock;
	output readWrite, enable;
	output [10:0]	address; 
	input [7:0]	dataOut;
	output [7:0] dataIn;
	
	reg readWrite, enable;
	reg [10:0]	address;
	reg [7:0]	dataIn;
	reg clock;

	parameter stimDelay = 20;
	integer i;
	initial // Response
	begin
		enable = 1'b1;
		address = 10'b0;
		dataIn = 8'b0;
		readWrite = 1'b0;
	end
	
	initial // Stimulus
	begin 
	enable = 1'b1; readWrite = 1'b0; clock = 1'b0;
	#stimDelay;
	
	for(i = 0; i < 128; i = i + 1) begin
		clock = 1;
		#stimDelay; dataIn = i; address = i;#stimDelay;
		clock = 0;
	end
	
	#stimDelay; enable = 1'b1; readWrite = 1'b1;#stimDelay;
	
	for(i = 0; i < 128; i = i + 1) begin
		#stimDelay; address = i;#stimDelay;
	end
	

	$finish; // finish simulation
	end
endmodule

assignment_3/sram/testbench/sram.vcd
$date
	Tue Feb 09 12:29:34 2016
$end
$version
	Icarus Verilog
$end
$timescale
	1s
$end
$scope module testBench $end
$scope module sram1 $end
$var wire 11 ! address [10:0] $end
$var wire 1 " clock $end
$var wire 8 # dataIn [7:0] $end
$var wire 8 $ dataOut [7:0] $end
$var wire 1 % enable $end
$var wire 1 & readWrite $end
$var integer 32 ' i [31:0] $end
$upscope $end
$upscope $end
$enddefinitions $end
#0
$dumpvars
b10000010 '
0&
1%
bz $
b0 #
0"
b0 !
$end
#20
1"
#60
1"
#80
b1 !
b1 #
#100
1"
#120
b10 !
b10 #
#140
1"
#160
b11 !
b11 #
#180
1"
#200
b100 !
b100 #
#220
1"
#240
b101 !
b101 #
#260
1"
#280
b110 !
b110 #
#300
1"
#320
b111 !
b111 #
#340
1"
#360
b1000 !
b1000 #
#380
1"
#400
b1001 !
b1001 #
#420
1"
#440
b1010 !
b1010 #
#460
1"
#480
b1011 !
b1011 #
#500
1"
#520
b1100 !
b1100 #
#540
1"
#560
b1101 !
b1101 #
#580
1"
#600
b1110 !
b1110 #
#620
1"
#640
b1111 !
b1111 #
#660
1"
#680
b10000 !
b10000 #
#700
1"
#720
b10001 !
b10001 #
#740
1"
#760
b10010 !
b10010 #
#780
1"
#800
b10011 !
b10011 #
#820
1"
#840
b10100 !
b10100 #
#860
1"
#880
b10101 !
b10101 #
#900
1"
#920
b10110 !
b10110 #
#940
1"
#960
b10111 !
b10111 #
#980
1"
#1000
b11000 !
b11000 #
#1020
1"
#1040
b11001 !
b11001 #
#1060
1"
#1080
b11010 !
b11010 #
#1100
1"
#1120
b11011 !
b11011 #
#1140
1"
#1160
b11100 !
b11100 #
#1180
1"
#1200
b11101 !
b11101 #
#1220
1"
#1240
b11110 !
b11110 #
#1260
1"
#1280
b11111 !
b11111 #
#1300
1"
#1320
b100000 !
b100000 #
#1340
1"
#1360
b100001 !
b100001 #
#1380
1"
#1400
b100010 !
b100010 #
#1420
1"
#1440
b100011 !
b100011 #
#1460
1"
#1480
b100100 !
b100100 #
#1500
1"
#1520
b100101 !
b100101 #
#1540
1"
#1560
b100110 !
b100110 #
#1580
1"
#1600
b100111 !
b100111 #
#1620
1"
#1640
b101000 !
b101000 #
#1660
1"
#1680
b101001 !
b101001 #
#1700
1"
#1720
b101010 !
b101010 #
#1740
1"
#1760
b101011 !
b101011 #
#1780
1"
#1800
b101100 !
b101100 #
#1820
1"
#1840
b101101 !
b101101 #
#1860
1"
#1880
b101110 !
b101110 #
#1900
1"
#1920
b101111 !
b101111 #
#1940
1"
#1960
b110000 !
b110000 #
#1980
1"
#2000
b110001 !
b110001 #
#2020
1"
#2040
b110010 !
b110010 #
#2060
1"
#2080
b110011 !
b110011 #
#2100
1"
#2120
b110100 !
b110100 #
#2140
1"
#2160
b110101 !
b110101 #
#2180
1"
#2200
b110110 !
b110110 #
#2220
1"
#2240
b110111 !
b110111 #
#2260
1"
#2280
b111000 !
b111000 #
#2300
1"
#2320
b111001 !
b111001 #
#2340
1"
#2360
b111010 !
b111010 #
#2380
1"
#2400
b111011 !
b111011 #
#2420
1"
#2440
b111100 !
b111100 #
#2460
1"
#2480
b111101 !
b111101 #
#2500
1"
#2520
b111110 !
b111110 #
#2540
1"
#2560
b111111 !
b111111 #
#2580
1"
#2600
b1000000 !
b1000000 #
#2620
1"
#2640
b1000001 !
b1000001 #
#2660
1"
#2680
b1000010 !
b1000010 #
#2700
1"
#2720
b1000011 !
b1000011 #
#2740
1"
#2760
b1000100 !
b1000100 #
#2780
1"
#2800
b1000101 !
b1000101 #
#2820
1"
#2840
b1000110 !
b1000110 #
#2860
1"
#2880
b1000111 !
b1000111 #
#2900
1"
#2920
b1001000 !
b1001000 #
#2940
1"
#2960
b1001001 !
b1001001 #
#2980
1"
#3000
b1001010 !
b1001010 #
#3020
1"
#3040
b1001011 !
b1001011 #
#3060
1"
#3080
b1001100 !
b1001100 #
#3100
1"
#3120
b1001101 !
b1001101 #
#3140
1"
#3160
b1001110 !
b1001110 #
#3180
1"
#3200
b1001111 !
b1001111 #
#3220
1"
#3240
b1010000 !
b1010000 #
#3260
1"
#3280
b1010001 !
b1010001 #
#3300
1"
#3320
b1010010 !
b1010010 #
#3340
1"
#3360
b1010011 !
b1010011 #
#3380
1"
#3400
b1010100 !
b1010100 #
#3420
1"
#3440
b1010101 !
b1010101 #
#3460
1"
#3480
b1010110 !
b1010110 #
#3500
1"
#3520
b1010111 !
b1010111 #
#3540
1"
#3560
b1011000 !
b1011000 #
#3580
1"
#3600
b1011001 !
b1011001 #
#3620
1"
#3640
b1011010 !
b1011010 #
#3660
1"
#3680
b1011011 !
b1011011 #
#3700
1"
#3720
b1011100 !
b1011100 #
#3740
1"
#3760
b1011101 !
b1011101 #
#3780
1"
#3800
b1011110 !
b1011110 #
#3820
1"
#3840
b1011111 !
b1011111 #
#3860
1"
#3880
b1100000 !
b1100000 #
#3900
1"
#3920
b1100001 !
b1100001 #
#3940
1"
#3960
b1100010 !
b1100010 #
#3980
1"
#4000
b1100011 !
b1100011 #
#4020
1"
#4040
b1100100 !
b1100100 #
#4060
1"
#4080
b1100101 !
b1100101 #
#4100
1"
#4120
b1100110 !
b1100110 #
#4140
1"
#4160
b1100111 !
b1100111 #
#4180
1"
#4200
b1101000 !
b1101000 #
#4220
1"
#4240
b1101001 !
b1101001 #
#4260
1"
#4280
b1101010 !
b1101010 #
#4300
1"
#4320
b1101011 !
b1101011 #
#4340
1"
#4360
b1101100 !
b1101100 #
#4380
1"
#4400
b1101101 !
b1101101 #
#4420
1"
#4440
b1101110 !
b1101110 #
#4460
1"
#4480
b1101111 !
b1101111 #
#4500
1"
#4520
b1110000 !
b1110000 #
#4540
1"
#4560
b1110001 !
b1110001 #
#4580
1"
#4600
b1110010 !
b1110010 #
#4620
1"
#4640
b1110011 !
b1110011 #
#4660
1"
#4680
b1110100 !
b1110100 #
#4700
1"
#4720
b1110101 !
b1110101 #
#4740
1"
#4760
b1110110 !
b1110110 #
#4780
1"
#4800
b1110111 !
b1110111 #
#4820
1"
#4840
b1111000 !
b1111000 #
#4860
1"
#4880
b1111001 !
b1111001 #
#4900
1"
#4920
b1111010 !
b1111010 #
#4940
1"
#4960
b1111011 !
b1111011 #
#4980
1"
#5000
b1111100 !
b1111100 #
#5020
1"
#5040
b1111101 !
b1111101 #
#5060
1"
#5080
b1111110 !
b1111110 #
#5100
1"
#5120
b1111111 !
b1111111 #
#5140
0"
#5160
bx $
1&
#5200
b0 $
b0 !
#5240
b1 $
b1 !
#5280
b10 $
b10 !
#5320
b11 $
b11 !
#5360
b100 $
b100 !
#5400
b101 $
b101 !
#5440
b110 $
b110 !
#5480
b111 $
b111 !
#5520
bx $
b1000 !
#5560
b1001 !
#5600
b1010 !
#5640
b1011 !
#5680
b1100 !
#5720
b1101 !
#5760
b1110 !
#5800
b1111 !
#5840
b10000 !
#5880
b10001 !
#5920
b10010 !
#5960
b10011 !
#6000
b10100 !
#6040
b10101 !
#6080
b10110 !
#6120
b10111 !
#6160
b11000 !
#6200
b11001 !
#6240
b11010 !
#6280
b11011 !
#6320
b11100 !
#6360
b11101 !
#6400
b11110 !
#6440
b11111 !
#6480
b100000 !
#6520
b100001 !
#6560
b100010 !
#6600
b100011 !
#6640
b100100 !
#6680
b100101 !
#6720
b100110 !
#6760
b100111 !
#6800
b101000 !
#6840
b101001 !
#6880
b101010 !
#6920
b101011 !
#6960
b101100 !
#7000
b101101 !
#7040
b101110 !
#7080
b101111 !
#7120
b110000 !
#7160
b110001 !
#7200
b110010 !
#7240
b110011 !
#7280
b110100 !
#7320
b110101 !
#7360
b110110 !
#7400
b110111 !
#7440
b111000 !
#7480
b111001 !
#7520
b111010 !
#7560
b111011 !
#7600
b111100 !
#7640
b111101 !
#7680
b111110 !
#7720
b111111 !
#7760
b1000000 !
#7800
b1000001 !
#7840
b1000010 !
#7880
b1000011 !
#7920
b1000100 !
#7960
b1000101 !
#8000
b1000110 !
#8040
b1000111 !
#8080
b1001000 !
#8120
b1001001 !
#8160
b1001010 !
#8200
b1001011 !
#8240
b1001100 !
#8280
b1001101 !
#8320
b1001110 !
#8360
b1001111 !
#8400
b1010000 !
#8440
b1010001 !
#8480
b1010010 !
#8520
b1010011 !
#8560
b1010100 !
#8600
b1010101 !
#8640
b1010110 !
#8680
b1010111 !
#8720
b1011000 !
#8760
b1011001 !
#8800
b1011010 !
#8840
b1011011 !
#8880
b1011100 !
#8920
b1011101 !
#8960
b1011110 !
#9000
b1011111 !
#9040
b1100000 !
#9080
b1100001 !
#9120
b1100010 !
#9160
b1100011 !
#9200
b1100100 !
#9240
b1100101 !
#9280
b1100110 !
#9320
b1100111 !
#9360
b1101000 !
#9400
b1101001 !
#9440
b1101010 !
#9480
b1101011 !
#9520
b1101100 !
#9560
b1101101 !
#9600
b1101110 !
#9640
b1101111 !
#9680
b1110000 !
#9720
b1110001 !
#9760
b1110010 !
#9800
b1110011 !
#9840
b1110100 !
#9880
b1110101 !
#9920
b1110110 !
#9960
b1110111 !
#10000
b1111000 !
#10040
b1111001 !
#10080
b1111010 !
#10120
b1111011 !
#10160
b1111100 !
#10200
b1111101 !
#10240
b1111110 !
#10280
b1111111 !
