assignment_2/Timer/timer.v
module timer(q, clk, rst);
	input clk, rst;
	output reg [0:2] q;
	
	always @(posedge clk)
	begin
		if(!rst)
			if(q != 3'b111)
				begin
					q <= q + 1;
				end
			else 
				begin
					q <= q;
				end
		else
			begin
				q <= 3'b000;
			end
	end

endmodule

assignment_2/Timer/timerTop.v
// timer.v
`include "timer.v"

module testBench;
 wire [0:2] q;
 wire clk, rst;
 
 timer theTime(q, clk, rst);
 Tester aTester(q, clk, rst);
 
 // file for gtkwave
 initial
 begin
 // these two files support gtkwave and are required
 $dumpfile("timer0.vcd");
 $dumpvars(1, theTime);
 end
endmodule

module Tester (q, clk, rst);

 input [0:2] q;
 output clk, rst;
 reg clk, rst;
 parameter stimDelay = 20;
 
 integer i;

 initial // Response
 begin
 $display("\t\t clk rst \t q \t Time ");
 $monitor("\t\t %b\t %b \t %b", clk, rst, q, $time );
 end

 initial // Stimulus
 begin
 clk = 0; rst = 0;
 #stimDelay clk = 1; rst = 1;
 #stimDelay clk = 0; rst = 0;
 #stimDelay clk = 1;

 for (i = 0; i < 16; i = i + 1) begin
	#stimDelay clk = 0;
	#stimDelay clk = 1;
 end

 #(2*stimDelay); // needed to see END of simulation
 $finish; // finish simulation
 end
endmodule

assignment_2/Timer/timer0.vcd
$date
	Thu Jan 21 09:31:44 2016
$end
$version
	Icarus Verilog
$end
$timescale
	1s
$end
$scope module testBench $end
$scope module theTime $end
$var wire 1 ! clk $end
$var wire 1 " rst $end
$var reg 3 # q [0:2] $end
$upscope $end
$upscope $end
$enddefinitions $end
#0
$dumpvars
bx #
0"
0!
$end
#20
b0 #
1"
1!
#40
0"
0!
#60
b1 #
1!
#80
0!
#100
b10 #
1!
#120
0!
#140
b11 #
1!
#160
0!
#180
b100 #
1!
#200
0!
#220
b101 #
1!
#240
0!
#260
b110 #
1!
#280
0!
#300
b111 #
1!
