assignment_1/iverilog/counterOne.v
module CounterOne(q, clk, rst);
	input clk, rst;
	output [0:3] q;
	output test;
	
	wire [0:3] qBar;
	
	//module DFlipFlop(q, qBar, D, clk, rst);
	DFlipFlop c0 (q[3], qBar[3], qBar[3], clk, rst);
	DFlipFlop c1 (q[2], qBar[2], qBar[2], q[3], rst);
	DFlipFlop c2 (q[1], qBar[1], qBar[1], q[2], rst);
	DFlipFlop c3 (q[0], qBar[0], qBar[0], q[1], rst);
endmodule

assignment_1/counter_2/quartas_gate/DFlipFlop.sv
module DFlipFlop(q, qBar, D, clk, rst);
	input D, clk, rst;
	output q, qBar;
	reg q;
	not n1 (qBar, q);
		always@ (negedge rst or posedge clk) begin
			if(!rst)
				q = 0;
			else
				q = D;
end endmodule

assignment_1/counter_2/quartas_gate/CounterTwo.sv
module CounterTwo(q, clk, rst);
	input clk, rst;
	output [3:0] q;
	
	wire [3:0] qBar;
	wire [3:0] d;
	
	//Gates for d[0];
	buf(d[0], qBar[0]);
	
	//Gates for d[1];
	xnor(d[1], q[0], q[1]);
	
	//Gates for d[2];
	wire q1OrLowerBits, q2AndLowerBitsOr, qBar2AndLowerBits;
	or(q1OrLowerBits, q[0], q[1]);
	and(q2AndLowerBitsOr, q[2], q1OrLowerBits);
	and(qBar2AndLowerBits, qBar[2], qBar[1], qBar[0]);
	or(d[2], qBar2AndLowerBits, q2AndLowerBitsOr);
	
	//Gates for d[3];
	wire q2OrLowerBits, q3AndLowerBitsOr, qBar3AndLowerBits;
	or(q2OrLowerBits, q[2], q[1], q[0]);
	and(q3AndLowerBitsOr, q[3], q2OrLowerBits);
	and(qBar3AndLowerBits, qBar[3], qBar[2], qBar[1], qBar[0]);
	or(d[3], qBar3AndLowerBits, q3AndLowerBitsOr);
	
	
	DFlipFlop c0 (q[0], qBar[0], d[0], clk, rst);
	DFlipFlop c1 (q[1], qBar[1], d[1], clk, rst);
	DFlipFlop c2 (q[2], qBar[2], d[2], clk, rst);
	DFlipFlop c3 (q[3], qBar[3], d[3], clk, rst);
endmodule

assignment_1/counter_2/iverilog/counterTwoTop.v
// counter.v
`include "DFlipFlop.v"
`include "counterOne.v"

module testBench;
 wire [3:0] q;
 wire clk, rst;
 
 CounterTwo counter(q, clk, rst);
 Tester aTester(q, clk, rst);
 
 // file for gtkwave
 initial
 begin
 // these two files support gtkwave and are required
 $dumpfile("counterOne0.vcd");
 $dumpvars(1, counter);
 end
endmodule

module Tester (q, clk, rst);

 input [3:0] q;
 output clk, rst;
 reg clk, rst;
 parameter stimDelay = 20;

 integer i;

 initial // Response
 begin
 $display("\t\t clk rst \t q \t Time ");
 $monitor("\t\t %b\t %b \t %b", clk, rst, q, $time );
 end

 initial // Stimulus
 begin
 clk = 0; rst = 0;
 #stimDelay clk = 1; rst = 1;
 
 for (i = 0; i < 16; i = i +1) begin
	#stimDelay clk = 0;
	#stimDelay clk = 1;
 end

 #(2*stimDelay); // needed to see END of simulation
 $finish; // finish simulation
 end
endmodule

assignment_1/counter_2/iverilog_gate/counterTwo0.vcd
$date
	Fri Jan 08 13:50:21 2016
$end
$version
	Icarus Verilog
$end
$timescale
	1s
$end
$scope module testBench $end
$scope module counter $end
$var wire 1 ! clk $end
$var wire 4 " d [3:0] $end
$var wire 4 # q [3:0] $end
$var wire 1 $ q1OrLowerBits $end
$var wire 1 % q2AndLowerBitsOr $end
$var wire 1 & q2OrLowerBits $end
$var wire 1 ' q3AndLowerBitsOr $end
$var wire 4 ( qBar [3:0] $end
$var wire 1 ) qBar2AndLowerBits $end
$var wire 1 * qBar3AndLowerBits $end
$var wire 1 + rst $end
$upscope $end
$upscope $end
$enddefinitions $end
#0
$dumpvars
0+
1*
1)
b1111 (
0'
0&
0%
0$
b0 #
b1111 "
0!
$end
#20
b1110 "
0)
0*
1'
1%
1$
1&
b0 (
b1111 #
1+
1!
#40
0!
#60
b1101 "
b1 (
b1110 #
1!
#80
0!
#100
b1100 "
b10 (
b1101 #
1!
#120
0!
#140
0%
b1011 "
0$
b11 (
b1100 #
1!
#160
0!
#180
b1010 "
1$
b100 (
b1011 #
1!
#200
0!
#220
b1001 "
b101 (
b1010 #
1!
#240
0!
#260
b1000 "
b110 (
b1001 #
1!
#280
0!
#300
1)
0'
b111 "
0$
0&
b111 (
b1000 #
1!
#320
0!
#340
b110 "
0)
1%
1$
1&
b1000 (
b111 #
1!
#360
0!
#380
b101 "
b1001 (
b110 #
1!
#400
0!
#420
b100 "
b1010 (
b101 #
1!
#440
0!
#460
0%
b11 "
0$
b1011 (
b100 #
1!
#480
0!
#500
b10 "
1$
b1100 (
b11 #
1!
#520
0!
#540
b1 "
b1101 (
b10 #
1!
#560
0!
#580
b0 "
b1110 (
b1 #
1!
#600
0!
#620
1)
1*
b1111 "
0$
0&
b1111 (
b0 #
1!
#640
0!
#660
b1110 "
0)
0*
1'
1%
1$
1&
b0 (
b1111 #
1!
