assignment_1/counter_1/quartas_structural/DFlipFlop.sv
module DFlipFlop(q, qBar, D, clk, rst);
	input D, clk, rst;
	output q, qBar;
	reg q;
	not n1 (qBar, q);
		always@ (negedge rst or posedge clk) begin
			if(!rst)
				q = 0;
			else
				q = D;
end endmodule 

// divided_clocks[0] = 25MHz, [1] = 12.5Mhz, ... [23] = 3Hz, [24] = 1.5Hz, [25] = 0.75Hz, ...
module clock_divider15 (clock, divided_clock15);
	input clock;
	output divided_clock15;
	reg [31:0] divided_clocks;

	initial
	divided_clocks = 0;

	always @(posedge clock)
	divided_clocks = divided_clocks + 1;
	assign divided_clock15 = divided_clocks[24];
endmodule

assignment_1/counter_1/iverilog/counterOne.v
module CounterOne(q, clk, rst);
	input clk, rst;
	output [3:0] q;
	output test;
	
	wire [3:0] qBar;
	
	DFlipFlop c0 (q[0], qBar[0], qBar[0], clk, rst);
	DFlipFlop c1 (q[1], qBar[1], qBar[1], q[0], rst);
	DFlipFlop c2 (q[2], qBar[2], qBar[2], q[1], rst);
	DFlipFlop c3 (q[3], qBar[3], qBar[3], q[2], rst);
endmodule

assignment_1/counter_1/iverilog_structural/counterOneTop.v
// counter.v
`include "DFlipFlop.v"
`include "counterOne.v"

module testBench;
 wire [3:0] q;
 wire clk, rst;
 
 CounterOne counter(q, clk, rst);
 Tester aTester(q, clk, rst);
 
 // file for gtkwave
 initial
 begin
 // these two files support gtkwave and are required
 $dumpfile("counterOne0.vcd");
 $dumpvars(1, counter);
 end
endmodule

module Tester (q, clk, rst);

 input [3:0] q;
 output clk, rst;
 reg clk, rst;
 parameter stimDelay = 20;

 integer i;

 initial // Response
 begin
 $display("\t\t clk rst \t q \t Time ");
 $monitor("\t\t %b\t %b \t %b", clk, rst, q, $time );
 end

 initial // Stimulus
 begin
 clk = 0; rst = 0;
 #stimDelay clk = 1; rst = 1;
 
 for (i = 0; i < 16; i = i +1) begin
	#stimDelay clk = 0;
	#stimDelay clk = 1;
 end

 #(2*stimDelay); // needed to see END of simulation
 $finish; // finish simulation
 end
endmodule

assignment_1/counter_1/iverilog_gate/counterOne0.vcd
$date
	Fri Jan 08 13:47:35 2016
$end
$version
	Icarus Verilog
$end
$timescale
	1s
$end
$scope module testBench $end
$scope module counter $end
$var wire 1 ! clk $end
$var wire 4 " q [3:0] $end
$var wire 4 # qBar [3:0] $end
$var wire 1 $ rst $end
$upscope $end
$upscope $end
$enddefinitions $end
#0
$dumpvars
0$
b1111 #
b0 "
0!
$end
#20
b0 #
b1111 "
1$
1!
#40
0!
#60
b1 #
b1110 "
1!
#80
0!
#100
b10 #
b1101 "
1!
#120
0!
#140
b11 #
b1100 "
1!
#160
0!
#180
b100 #
b1011 "
1!
#200
0!
#220
b101 #
b1010 "
1!
#240
0!
#260
b110 #
b1001 "
1!
#280
0!
#300
b111 #
b1000 "
1!
#320
0!
#340
b1000 #
b111 "
1!
#360
0!
#380
b1001 #
b110 "
1!
#400
0!
#420
b1010 #
b101 "
1!
#440
0!
#460
b1011 #
b100 "
1!
#480
0!
#500
b1100 #
b11 "
1!
#520
0!
#540
b1101 #
b10 "
1!
#560
0!
#580
b1110 #
b1 "
1!
#600
0!
#620
b1111 #
b0 "
1!
#640
0!
#660
b0 #
b1111 "
1!
