assignment_1/counter_2/quartas_gate/DFlipFlop.sv
module DFlipFlop(q, qBar, D, clk, rst);
	input D, clk, rst;
	output q, qBar;
	reg q;
	not n1 (qBar, q);
		always@ (negedge rst or posedge clk) begin
			if(!rst)
				q = 0;
			else
				q = D;
end endmodule

assignment_1/counter_3/iverilog_gate/counterThree.v
module CounterThree(q, clk, rst);
	input clk, rst;
	output [0:3] q;

	wire [3:0] qBar;

	DFlipFlop c0 (q[0], qBar[0], q[1], clk, rst);
	DFlipFlop c1 (q[1], qBar[1], q[2], clk, rst);
	DFlipFlop c2 (q[2], qBar[2], q[3], clk, rst);
	DFlipFlop c3 (q[3], qBar[3], qBar[0], clk, rst);
endmodule

assignment_1/counter_3/iverilog_gate/counterThreeTop.v
// counter.v
`include "counterThree.v"
`include "DFlipFlop.v"

module testBench;
 wire [0:3] q;
 wire clk, rst;
 
 CounterThree counter(q, clk, rst);
 Tester aTester(q, clk, rst);
 
 // file for gtkwave
 initial
 begin
 // these two files support gtkwave and are required
 $dumpfile("counterThree0.vcd");
 $dumpvars(1, counter);
 end
endmodule

module Tester (q, clk, rst);

 input [0:3] q;
 output clk, rst;
 reg clk, rst;
 parameter stimDelay = 20;
 
 integer i;

 initial // Response
 begin
 $display("\t\t clk rst \t q \t Time ");
 $monitor("\t\t %b\t %b \t %b", clk, rst, q, $time );
 end

 initial // Stimulus
 begin
 clk = 0; rst = 0;
 #stimDelay clk = 1; rst = 1;

 for (i = 0; i < 16; i = i + 1) begin
	#stimDelay clk = 0;
	#stimDelay clk = 1;
 end

 #(2*stimDelay); // needed to see END of simulation
 $finish; // finish simulation
 end
endmodule

assignment_1/counter_3/iverilog_gate/counterThree0.vcd
$date
	Mon Jan 11 15:04:32 2016
$end
$version
	Icarus Verilog
$end
$timescale
	1s
$end
$scope module testBench $end
$scope module counter $end
$var wire 1 ! clk $end
$var wire 1 " rst $end
$var wire 4 # qBar [3:0] $end
$var wire 4 $ q [0:3] $end
$upscope $end
$upscope $end
$enddefinitions $end
#0
$dumpvars
b0 $
b1111 #
0"
0!
$end
#20
b111 #
b1 $
1"
1!
#40
0!
#60
b11 #
b11 $
1!
#80
0!
#100
b1 #
b111 $
1!
#120
0!
#140
b0 #
b1111 $
1!
#160
0!
#180
b1000 #
b1110 $
1!
#200
0!
#220
b1100 #
b1100 $
1!
#240
0!
#260
b1110 #
b1000 $
1!
#280
0!
#300
b1111 #
b0 $
1!
#320
0!
#340
b111 #
b1 $
1!
#360
0!
#380
b11 #
b11 $
1!
#400
0!
#420
b1 #
b111 $
1!
#440
0!
#460
b0 #
b1111 $
1!
#480
0!
#500
b1000 #
b1110 $
1!
#520
0!
#540
b1100 #
b1100 $
1!
#560
0!
#580
b1110 #
b1000 $
1!
#600
0!
#620
b1111 #
b0 $
1!
#640
0!
#660
b111 #
b1 $
1!
