assignment_5/Host_Server Code/gameClock.v
/*
Bryan Bednarski
EE 371 Prof. Peckol Winter 2016
Project 5: Final Project Game

gameClock.v
This module controls the clock that our C code will base its decision making timeline from.
*/

module gameClock(clk, reset, gameTime); // input 50MhZ clk divided 22 times to 11.9Hz ~~ 83ms
	input clk, reset;
	output reg [31:0] gameTime;
	
	initial begin
		gameTime = 32'b0;
	end
		
	always@(posedge clk) begin
		if (reset)
			gameTime <= 32'b0;
		else
			gameTime <= gameTime + 32'b1;
	end
	
endmodule
	
	
/* // divided_clocks[0] = 25MHz, [1] = 12.5Mhz, ... [23] = 3Hz, [24] = 1.5Hz, [25] = 0.75Hz, ...
module clock_divider (clock, divided_clocks);
	input clock;
	output [31:0] divided_clocks;
	reg [31:0] divided_clocks;
	initial divided_clocks = 0;
	always @(posedge clock)
		divided_clocks = divided_clocks + 1;
endmodule 

// Generate clk off of CLOCK_50, whichClock picks rate.
wire [31:0] clk;
parameter whichClock = 8;
clock_divider cdiv (CLOCK_50, clk); */

assignment_5/Host_Server Code/gameClockTestbench.v
/*	Bryan Bednarski
	EE 371 Peckol Winter 2016
	Project 5: Space Invaders
	gameClockTestbecnh.v
	
	This .v file represents a top-level testbench for the gameClock.v file.
	This modules beings counting when the program is run so that our software program can track elapsed time.
*/

`include "gameClock.v"

module gameClockTestbench;
	// connect the two modules
	wire 		    clk, reset;
	wire [31:0] 	gameTime;
	
	// declare an instance of the module
	gameClock gcTest(clk, reset, gameTime);

	// declare an instance of the Tester module
	Tester test1(clk, reset, gameTime);
	
	// file specifications for gtkwave
	initial
		begin
		// dump file is for dumping all the variables in a simulation
		$dumpfile("gameClock.vcd");
		
		// dumps all the variables in module myDesign and below
		// but not modules instantiated in myDesign into the dump file.
		$dumpvars(1, gcTest);
		end

endmodule

module Tester (clk, reset, gameTime);

	input 	[31:0]			gameTime;
	output	reg	 			clk, reset;
		
	parameter stimDelay = 10;
	
	initial begin 
		$display("clk reset \t gameTime \t Time");
		$monitor("\t %b \t %b \t %b \t", clk, reset, gameTime, $time);
	end
	
	always #stimDelay clk = ~clk;
	
	initial begin // Stimulus 
		#(stimDelay);  clk = 0; reset = 0;
		//#(stimDelay);  reset = 1;
		#(stimDelay);  reset = 0;
		#(100*stimDelay);
		
		$finish; 						// finish simulation
	end

endmodule

assignment_5/Host_Server Code/gameClock.vcd
$date
	Sun Mar 06 17:05:42 2016
$end
$version
	Icarus Verilog
$end
$timescale
	1s
$end
$scope module gameClockTestbench $end
$scope module gcTest $end
$var wire 1 ! reset $end
$var wire 1 " clk $end
$var reg 32 # gameTime [31:0] $end
$upscope $end
$upscope $end
$enddefinitions $end
#0
$dumpvars
b0 #
x"
x!
$end
#10
0!
0"
#20
b1 #
1"
#30
0"
#40
b10 #
1"
#50
0"
#60
b11 #
1"
#70
0"
#80
b100 #
1"
#90
0"
#100
b101 #
1"
#110
0"
#120
b110 #
1"
#130
0"
#140
b111 #
1"
#150
0"
#160
b1000 #
1"
#170
0"
#180
b1001 #
1"
#190
0"
#200
b1010 #
1"
#210
0"
#220
b1011 #
1"
#230
0"
#240
b1100 #
1"
#250
0"
#260
b1101 #
1"
#270
0"
#280
b1110 #
1"
#290
0"
#300
b1111 #
1"
#310
0"
#320
b10000 #
1"
#330
0"
#340
b10001 #
1"
#350
0"
#360
b10010 #
1"
#370
0"
#380
b10011 #
1"
#390
0"
#400
b10100 #
1"
#410
0"
#420
b10101 #
1"
#430
0"
#440
b10110 #
1"
#450
0"
#460
b10111 #
1"
#470
0"
#480
b11000 #
1"
#490
0"
#500
b11001 #
1"
#510
0"
#520
b11010 #
1"
#530
0"
#540
b11011 #
1"
#550
0"
#560
b11100 #
1"
#570
0"
#580
b11101 #
1"
#590
0"
#600
b11110 #
1"
#610
0"
#620
b11111 #
1"
#630
0"
#640
b100000 #
1"
#650
0"
#660
b100001 #
1"
#670
0"
#680
b100010 #
1"
#690
0"
#700
b100011 #
1"
#710
0"
#720
b100100 #
1"
#730
0"
#740
b100101 #
1"
#750
0"
#760
b100110 #
1"
#770
0"
#780
b100111 #
1"
#790
0"
#800
b101000 #
1"
#810
0"
#820
b101001 #
1"
#830
0"
#840
b101010 #
1"
#850
0"
#860
b101011 #
1"
#870
0"
#880
b101100 #
1"
#890
0"
#900
b101101 #
1"
#910
0"
#920
b101110 #
1"
#930
0"
#940
b101111 #
1"
#950
0"
#960
b110000 #
1"
#970
0"
#980
b110001 #
1"
#990
0"
#1000
b110010 #
1"
#1010
0"
#1020
b110011 #
1"
