assignment_4/lab4/serial_com_code/Counter4.sv
module Counter4(q, clk, rst);
	
	input clk, rst;
	output reg [3:0] q = 4'b0000;
	
	wire [3:0] qBar;
	
	//DFlipFlop c0 (q[0], qBar[0], qBar[0], clk, rst);
	//DFlipFlop c1 (q[1], qBar[1], (qBar[0] & qBar[1]) | (q[1] & q[0]), clk, rst);
	//DFlipFlop c2 (q[2], qBar[2], (qBar[0] & qBar[1] & qBar[2]) | (q[2] & q[0]) | (q[2] & q[1]), clk, rst);
	//DFlipFlop c3 (q[3], qBar[3], (qBar[0] & qBar[1] & qBar[2] & qBar[3]) | (q[3] & q[0]) | (q[3] & q[1]) | (q[3] & q[2]), clk, rst);
	
	always @(posedge clk or posedge rst) begin
		if(rst)
			q <= 4'b0000;
		else begin
			if(q != 4'b1111)
				q <= q + 1;
			else
				q <= 4'b0000;
		end
	end
	
endmodule

assignment_4/lab4/serial_com_code/tests/Counter4_Test.v
// counter.v
`include "../DFlipFlop.sv"
`include "../Counter4.sv"

module testBench;
	wire [3:0] q;
	wire clk, rst;

	Counter4 counter(q, clk, rst);
	Tester aTester(q, clk, rst);

	// file for gtkwave
	initial begin
		// these two files support gtkwave and are required
		$dumpfile("vvp/counter4.vcd");
		$dumpvars(1, counter);
	end
endmodule

module Tester (q, clk, rst);
	input [3:0] q;
	output clk, rst;
	reg clk, rst;
	parameter stimDelay = 20;

	integer i;

	initial begin // Response
		$display("\t\t clk rst \t q \t Time ");
		$monitor("\t\t %b\t %b \t %b", clk, rst, q, $time );
	end

	initial begin // Stimulus 
		clk = 0; rst = 0;
		#stimDelay clk = 1; rst = 1;
		#stimDelay clk = 1; rst = 0;

		for (i = 0; i < 16; i = i +1) begin
			#stimDelay clk = 0;
			#stimDelay clk = 1;
	end

	#(2*stimDelay); // needed to see END of simulation
	$finish; // finish simulation
	end
endmodule

assignment_4/lab4/serial_com_code/tests/vvp/counter4.vcd
$date
	Tue Feb 16 13:38:20 2016
$end
$version
	Icarus Verilog
$end
$timescale
	1s
$end
$scope module testBench $end
$scope module counter $end
$var wire 1 ! clk $end
$var wire 1 " rst $end
$var reg 4 # q [3:0] $end
$upscope $end
$upscope $end
$enddefinitions $end
#0
$dumpvars
b0 #
0"
0!
$end
#20
1"
1!
#40
0"
#60
0!
#80
b1 #
1!
#100
0!
#120
b10 #
1!
#140
0!
#160
b11 #
1!
#180
0!
#200
b100 #
1!
#220
0!
#240
b101 #
1!
#260
0!
#280
b110 #
1!
#300
0!
#320
b111 #
1!
#340
0!
#360
b1000 #
1!
#380
0!
#400
b1001 #
1!
#420
0!
#440
b1010 #
1!
#460
0!
#480
b1011 #
1!
#500
0!
#520
b1100 #
1!
#540
0!
#560
b1101 #
1!
#580
0!
#600
b1110 #
1!
#620
0!
#640
b1111 #
1!
#660
0!
#680
b0 #
1!
