assignment_4/lab4/serial_com_code/Counter4.sv
module Counter4(q, clk, rst);
	
	input clk, rst;
	output reg [3:0] q = 4'b0000;
	
	wire [3:0] qBar;
	
	//DFlipFlop c0 (q[0], qBar[0], qBar[0], clk, rst);
	//DFlipFlop c1 (q[1], qBar[1], (qBar[0] & qBar[1]) | (q[1] & q[0]), clk, rst);
	//DFlipFlop c2 (q[2], qBar[2], (qBar[0] & qBar[1] & qBar[2]) | (q[2] & q[0]) | (q[2] & q[1]), clk, rst);
	//DFlipFlop c3 (q[3], qBar[3], (qBar[0] & qBar[1] & qBar[2] & qBar[3]) | (q[3] & q[0]) | (q[3] & q[1]) | (q[3] & q[2]), clk, rst);
	
	always @(posedge clk or posedge rst) begin
		if(rst)
			q <= 4'b0000;
		else begin
			if(q != 4'b1111)
				q <= q + 1;
			else
				q <= 4'b0000;
		end
	end
	
endmodule

assignment_4/lab4/serial_com_code/BitIdentifierCount.sv
module BitIdentifierCount(identifer, enable, bscClk);
	input enable, bscClk;
	output [7:0] identifer;
	
endmodule

assignment_4/lab4/serial_com_code/shiftBufferReceive.sv
module shiftBufferReceive(dataIn, SRclock, dataBus);
	input dataIn, SRclock;
	output [7:0] dataBus;
	
	reg [7:0] temp = 0;
	
	always@(posedge SRclock) begin
		temp = temp << 1;
		temp[0] = dataIn;
	end
	assign dataBus = temp;
endmodule

assignment_4/lab4/serial_com_code/BitSampleCount.sv
module BitSampleCount(srcc, bic, rstBSC, clk);
	input rstBSC, clk;
	output reg srcc, bic;
	
	
	wire [3:0] counterOut;
	Counter4 counter(counterOut, clk, rstBSC);
	
	always @(posedge clk) begin
		if (counterOut == 15) begin
			bic <= 1;
			srcc <= 0;
		end else if (counterOut == 7) begin
			bic <= 0;
			srcc <= 1;
		end else begin
			bic <= 0;
			srcc <= 0;
		end
	end
endmodule

assignment_4/lab4/serial_com_code/StartBitDetect.sv
module StartBitDetect(writingChar, data, reset, clock);
	input data, reset, clock;
	output reg writingChar = 1'b0;
	
	always @(posedge clock) begin
		if(reset) begin
			writingChar <= 1'b0;
		end else if((~writingChar) & data) begin
			writingChar <= 1'b1;
		end
	end
 
endmodule

assignment_4/lab4/serial_com_code/SerialInput.sv
module SerialInput(parallelOut, charRecieved, data, clock);
	input data, clock;
	output [7:0] parallelOut;
	output charRecieved;
	
	wire readingChar;
	wire [3:0] identifer;
	wire srClock, bicClock;
	wire [3:0] counter4;
	
	StartBitDetect startDetect(readingChar, data, (charRecieved) && (counter4 == 4'b1111), clock);
	
	BitSampleCount bsc(srClock, bicClock, (~readingChar) | charRecieved, clock);
	shiftBufferReceive sbr(data, srClock, parallelOut);
	BitIdentifierCount bic(charRecieved, identifer, ~readingChar, bicClock);
	
	Counter4 c4(counter4, clock, ~charRecieved);
	
endmodule

assignment_4/lab4/serial_com_code/tests/SerialInput_Test.v
`include "../Counter4.sv"
`include "../StartBitDetect.sv"
`include "../BitIdentifierCount.sv"
`include "../BitSampleCount.sv"
`include "../ShiftBufferReceive.sv"
`include "../SerialInput.sv"

module testBench;
	wire [7:0] parallelOut;
	wire charRecieved;
	wire data, clock;

	SerialInput si(parallelOut, charRecieved, data, clock);
	Tester aTester(parallelOut, charRecieved, data, clock);

	// file for gtkwave
	initial begin
		// these two files support gtkwave and are required
		$dumpfile("vvp/serialinput.vcd");
		$dumpvars(1, si);
	end
endmodule

module Tester (parallelOut, charRecieved, data, clock);
	input [7:0] parallelOut;
	input charRecieved;
	output data, clock;
	reg data, clock;
	parameter stimDelay = 1;

	integer i, j;
	wire [0:7] testChar = 8'b11110000;

	initial begin // Response
		$display("\t\t clk \t data \t charRecieved \t \t parallelOut");
		$monitor("\t\t %b\t %b \t %b \t %b \t %b", clock, data, charRecieved, parallelOut, $time );
	end
	
	initial begin // Stimulus 
		clock = 0; data = 0;
		
		for(i = 0; i < 20; i = i + 1) begin
			#stimDelay clock = 0; #stimDelay clock = 1;
		end
		
		data = 1;
		for(i = 0; i < 16; i = i + 1) begin
			#stimDelay clock = 0; #stimDelay clock = 1;
		end

		for(j = 0; j < 8; j = j + 1) begin
			data = testChar[j];
			for(i = 0; i < 16; i = i + 1) begin
				#stimDelay clock = 0; #stimDelay clock = 1;
			end
		end
		
		data = 0;
		for(i = 0; i < 20; i = i + 1) begin
			#stimDelay clock = 0; #stimDelay clock = 1;
		end

	#(2*stimDelay); // needed to see END of simulation
	$finish; // finish simulation
	end
endmodule

assignment_4/lab4/serial_com_code/tests/vvp/serialinput.vcd
$date
	Tue Feb 23 05:46:02 2016
$end
$version
	Icarus Verilog
$end
$timescale
	1s
$end
$scope module testBench $end
$scope module si $end
$var wire 1 ! clock $end
$var wire 1 " data $end
$var wire 1 # srClock $end
$var wire 1 $ readingChar $end
$var wire 8 % parallelOut [7:0] $end
$var wire 4 & identifer [3:0] $end
$var wire 4 ' counter4 [3:0] $end
$var wire 1 ( charRecieved $end
$var wire 1 ) bicClock $end
$upscope $end
$upscope $end
$enddefinitions $end
#0
$dumpvars
0)
0(
b0 '
b0 &
b0 %
0$
0#
0"
0!
$end
#2
1!
#3
0!
#4
1!
#5
0!
#6
1!
#7
0!
#8
1!
#9
0!
#10
1!
#11
0!
#12
1!
#13
0!
#14
1!
#15
0!
#16
1!
#17
0!
#18
1!
#19
0!
#20
1!
#21
0!
#22
1!
#23
0!
#24
1!
#25
0!
#26
1!
#27
0!
#28
1!
#29
0!
#30
1!
#31
0!
#32
1!
#33
0!
#34
1!
#35
0!
#36
1!
#37
0!
#38
1!
#39
0!
#40
1"
1!
#41
0!
#42
1!
#43
0!
#44
1!
#45
0!
#46
1!
#47
0!
#48
1!
#49
0!
#50
1!
#51
0!
#52
1!
#53
0!
#54
1!
#55
0!
#56
1!
#57
0!
#58
1!
#59
0!
#60
1!
#61
0!
#62
1!
#63
0!
#64
1!
#65
0!
#66
1!
#67
0!
#68
1!
#69
0!
#70
1!
#71
0!
#72
1$
1!
#73
0!
#74
1!
#75
0!
#76
1!
#77
0!
#78
1!
#79
0!
#80
1!
#81
0!
#82
1!
#83
0!
#84
1!
#85
0!
#86
1!
#87
0!
#88
b1 %
1#
1!
#89
0!
#90
0#
1!
#91
0!
#92
1!
#93
0!
#94
1!
#95
0!
#96
1!
#97
0!
#98
1!
#99
0!
#100
1!
#101
0!
#102
1!
#103
0!
#104
b1 &
1)
1!
#105
0!
#106
0)
1!
#107
0!
#108
1!
#109
0!
#110
1!
#111
0!
#112
1!
#113
0!
#114
1!
#115
0!
#116
1!
#117
0!
#118
1!
#119
0!
#120
b11 %
1#
1!
#121
0!
#122
0#
1!
#123
0!
#124
1!
#125
0!
#126
1!
#127
0!
#128
1!
#129
0!
#130
1!
#131
0!
#132
1!
#133
0!
#134
1!
#135
0!
#136
b10 &
1)
1!
#137
0!
#138
0)
1!
#139
0!
#140
1!
#141
0!
#142
1!
#143
0!
#144
1!
#145
0!
#146
1!
#147
0!
#148
1!
#149
0!
#150
1!
#151
0!
#152
b111 %
1#
1!
#153
0!
#154
0#
1!
#155
0!
#156
1!
#157
0!
#158
1!
#159
0!
#160
1!
#161
0!
#162
1!
#163
0!
#164
1!
#165
0!
#166
1!
#167
0!
#168
b11 &
1)
1!
#169
0!
#170
0)
1!
#171
0!
#172
1!
#173
0!
#174
1!
#175
0!
#176
1!
#177
0!
#178
1!
#179
0!
#180
1!
#181
0!
#182
1!
#183
0!
#184
b1111 %
1#
1!
#185
0!
#186
0#
1!
#187
0!
#188
1!
#189
0!
#190
1!
#191
0!
#192
1!
#193
0!
#194
1!
#195
0!
#196
1!
#197
0!
#198
1!
#199
0!
#200
b100 &
1)
0"
1!
#201
0!
#202
0)
1!
#203
0!
#204
1!
#205
0!
#206
1!
#207
0!
#208
1!
#209
0!
#210
1!
#211
0!
#212
1!
#213
0!
#214
1!
#215
0!
#216
b11110 %
1#
1!
#217
0!
#218
0#
1!
#219
0!
#220
1!
#221
0!
#222
1!
#223
0!
#224
1!
#225
0!
#226
1!
#227
0!
#228
1!
#229
0!
#230
1!
#231
0!
#232
b101 &
1)
1!
#233
0!
#234
0)
1!
#235
0!
#236
1!
#237
0!
#238
1!
#239
0!
#240
1!
#241
0!
#242
1!
#243
0!
#244
1!
#245
0!
#246
1!
#247
0!
#248
b111100 %
1#
1!
#249
0!
#250
0#
1!
#251
0!
#252
1!
#253
0!
#254
1!
#255
0!
#256
1!
#257
0!
#258
1!
#259
0!
#260
1!
#261
0!
#262
1!
#263
0!
#264
b110 &
1)
1!
#265
0!
#266
0)
1!
#267
0!
#268
1!
#269
0!
#270
1!
#271
0!
#272
1!
#273
0!
#274
1!
#275
0!
#276
1!
#277
0!
#278
1!
#279
0!
#280
b1111000 %
1#
1!
#281
0!
#282
0#
1!
#283
0!
#284
1!
#285
0!
#286
1!
#287
0!
#288
1!
#289
0!
#290
1!
#291
0!
#292
1!
#293
0!
#294
1!
#295
0!
#296
b111 &
1)
1!
#297
0!
#298
0)
1!
#299
0!
#300
1!
#301
0!
#302
1!
#303
0!
#304
1!
#305
0!
#306
1!
#307
0!
#308
1!
#309
0!
#310
1!
#311
0!
#312
b11110000 %
1#
1!
#313
0!
#314
0#
1!
#315
0!
#316
1!
#317
0!
#318
1!
#319
0!
#320
1!
#321
0!
#322
1!
#323
0!
#324
1!
#325
0!
#326
1!
#327
0!
#328
1(
b1000 &
0)
1!
#329
0!
#330
b1 '
1!
#331
0!
#332
b10 '
1!
#333
0!
#334
b11 '
1!
#335
0!
#336
b100 '
1!
#337
0!
#338
b101 '
1!
#339
0!
#340
b110 '
1!
#341
0!
#342
b111 '
1!
#343
0!
#344
b1000 '
1!
#345
0!
#346
b1001 '
1!
#347
0!
#348
b1010 '
1!
#349
0!
#350
b1011 '
1!
#351
0!
#352
b1100 '
1!
#353
0!
#354
b1101 '
1!
#355
0!
#356
b1110 '
1!
#357
0!
#358
b1111 '
1!
#359
0!
#360
0(
b0 &
b0 '
0$
1!
