assignment_2/iVerilog/Timer.v
module Timer(clk, rst, stopVal, done);
	input clk, rst;
	input [0:2] stopVal;
	output reg done;
	
	reg [0:2] q;
	
	always @(*) begin
		done <= (q == stopVal);
	end
	
	always @(posedge clk) begin
		if(rst)
			q <= 3'b000;
		else begin
			if(q != stopVal)
				q <= q + 1;
			else
				q <= q;
		end
	end

endmodule

assignment_2/iVerilog/Arriving.v
`include "Timer.v"

module Arriving(clk, rst, arriveCtrl, arriving, departing, innerDoor, outerDoor, pressurized, evacuated);
	input clk, rst;
	input arriveCtrl, departing, innerDoor, outerDoor, pressurized, evacuated;
	output reg arriving;
	
	reg [3:0] ps;
	reg [3:0] ns;
	
	parameter reset = 3'b000;
	parameter min5 = 3'b001;
	parameter pres = 3'b010;
	parameter openOut = 3'b011;
	parameter evac = 3'b100;
	parameter openIn = 3'b101;
	
	Timer t(clk, arriveCtrl & !done, 3'b101, done);
	
	always @(*) 
		case(ps)
			reset: if(arriveCtrl) begin 
				ns = min5;
				arriving = 1; end
			else begin 
				ns = reset;
				arriving = 0; end
			
			min5: if(done) ns = pres;
			else ns = min5;
			
			pres: if(pressurized) ns = openOut;
			else ns = pres;
			
			openOut: if(outerDoor) ns = evac;
			else ns = openOut;
			
			evac: if(evacuated) ns = openIn;
			else ns = evac;
			
			openIn: if(innerDoor) ns = reset;
			else ns = openIn;
			
			default ns = ps;
	endcase
	
	always@(posedge clk) begin
		if(rst) begin
			ps <= reset;
		end begin
			ps <= ns;
		end
	end
endmodule

assignment_2/iVerilog/Arriving_Test.v
// counter.v
`include "Arriving.v"

module testBench;
	wire clk, rst;
	wire arriveCtrl;
	wire arriving;
	wire departing, innerDoor, outerDoor, pressurized, evacuated;

	Arriving p(clk, rst, arriveCtrl, arriving, departing, innerDoor, outerDoor, pressurized, evacuated);
	Tester aTester(clk, rst, arriveCtrl, arriving, departing, innerDoor, outerDoor, pressurized, evacuated);

	// file for gtkwave
	initial begin
		// these two files support gtkwave and are required
		$dumpfile("arriving.vcd");
		$dumpvars(1, p);
	end
endmodule

module Tester (clk, rst, arriveCtrl, arriving, departing, innerDoor, outerDoor, pressurized, evacuated);
 input arriving;
 output clk, rst;
 output arriveCtrl, departing, innerDoor, outerDoor, pressurized, evacuated;
 
 reg clk, rst;
 reg arriveCtrl, departing, innerDoor, outerDoor, pressurized, evacuated;
 parameter stimDelay = 20;

 initial // Response
 begin
 $display("\t\t clk rst \t arriving \t Time ");
 $monitor("\t\t %b\t %b \t %b", clk, rst, arriving, $time );
 end

 initial // Stimulus
 begin
 clk = 0; rst = 0; arriveCtrl = 0; departing = 0; innerDoor = 0; outerDoor = 0; pressurized = 0; evacuated = 0;
 
 clk = 0; #stimDelay clk = 1; rst = 1; #stimDelay
 clk = 0; #stimDelay clk = 1; rst = 0; #stimDelay
 clk = 0; #stimDelay clk = 1; arriveCtrl = 1; #stimDelay
 
 clk = 0; #stimDelay clk = 1; arriveCtrl = 0; #stimDelay
 clk = 0; #stimDelay clk = 1; #stimDelay
 clk = 0; #stimDelay clk = 1; #stimDelay
 clk = 0; #stimDelay clk = 1; #stimDelay
 clk = 0; #stimDelay clk = 1; #stimDelay
 clk = 0; #stimDelay clk = 1; #stimDelay
 clk = 0; #stimDelay clk = 1; #stimDelay
 clk = 0; #stimDelay clk = 1; #stimDelay
 clk = 0; #stimDelay clk = 1; #stimDelay
 clk = 0; #stimDelay clk = 1; #stimDelay
 clk = 0; #stimDelay clk = 1; #stimDelay
 clk = 0; #stimDelay clk = 1; #stimDelay
 clk = 0; #stimDelay clk = 1; pressurized = 1; #stimDelay
 clk = 0; #stimDelay clk = 1; #stimDelay
 clk = 0; #stimDelay clk = 1; #stimDelay
 clk = 0; #stimDelay clk = 1; outerDoor = 1; #stimDelay
 clk = 0; #stimDelay clk = 1; #stimDelay
 clk = 0; #stimDelay clk = 1; #stimDelay
 clk = 0; #stimDelay clk = 1; evacuated = 1; #stimDelay
 clk = 0; #stimDelay clk = 1; #stimDelay
 clk = 0; #stimDelay clk = 1; #stimDelay
 clk = 0; #stimDelay clk = 1; #stimDelay
 clk = 0; #stimDelay clk = 1; innerDoor = 1; #stimDelay
 clk = 0; #stimDelay clk = 1; #stimDelay
 clk = 0; #stimDelay clk = 1; #stimDelay

 #(2*stimDelay); // needed to see END of simulation
 $finish; // finish simulation
 end
endmodule

assignment_2/iVerilog/arriving.vcd
$date
	Sat Jan 23 12:06:51 2016
$end
$version
	Icarus Verilog
$end
$timescale
	1s
$end
$scope module testBench $end
$scope module p $end
$var wire 1 ! arriveCtrl $end
$var wire 1 " clk $end
$var wire 1 # departing $end
$var wire 1 $ evacuated $end
$var wire 1 % innerDoor $end
$var wire 1 & outerDoor $end
$var wire 1 ' pressurized $end
$var wire 1 ( rst $end
$var wire 1 ) done $end
$var reg 1 * arriving $end
$var reg 4 + ns [3:0] $end
$var reg 4 , ps [3:0] $end
$upscope $end
$upscope $end
$enddefinitions $end
#0
$dumpvars
bx ,
bx +
x*
x)
0(
0'
0&
0%
0$
0#
0"
0!
$end
#20
bx ,
1(
1"
#40
0"
#60
0(
1"
#80
0"
#100
1!
1"
#120
0"
#140
0!
1"
#160
0"
#180
1"
#200
0"
#220
1"
#240
0"
#260
1"
#280
0"
#300
1"
#320
0"
#340
1"
#360
0"
#380
1"
#400
0"
#420
1"
#440
0"
#460
1"
#480
0"
#500
1"
#520
0"
#540
1"
#560
0"
#580
1"
#600
0"
#620
1'
1"
#640
0"
#660
1"
#680
0"
#700
1"
#720
0"
#740
1&
1"
#760
0"
#780
1"
#800
0"
#820
1"
#840
0"
#860
1$
1"
#880
0"
#900
1"
#920
0"
#940
1"
#960
0"
#980
1"
#1000
0"
#1020
1%
1"
