assignment_2/iVerilog/Timer.v
module Timer(clk, rst, stopVal, done);
	input clk, rst;
	input [0:2] stopVal;
	output reg done;
	
	reg [0:2] q;
	
	always @(*) begin
		done <= (q == stopVal);
	end
	
	always @(posedge clk) begin
		if(rst)
			q <= 3'b000;
		else begin
			if(q != stopVal)
				q <= q + 1;
			else
				q <= q;
		end
	end

endmodule

assignment_2/iVerilog/Chamber.v
//Pressurize p(clk, rst, pressurizeCtrl, pressurized, evacuated);
//Evacuate e(clk, rst, evacuateCtrl, pressurized, evacuated);
module Chamber(clk, rst, pressurizeCtrl, evacuateCtrl, pressurized, evacuated);
	input clk, rst;
	input pressurizeCtrl, evacuateCtrl;
	output reg pressurized, evacuated;
	
	wire pDone, eDone;
	reg pressurizing, evacuating;
	
	Timer tP(clk, pressurizeCtrl, 'b110, pDone);
	Timer tE(clk, evacuateCtrl, 'b110, eDone);
	
	always @(posedge clk) begin
		if(evacuated & pressurizeCtrl) begin
			evacuated <= 0;
			pressurizing <= 1;
		end
		
		if(pressurizing & pDone) begin
			pressurized <= 1;
			pressurizing <= 0;
		end
		
		if(pressurized & evacuateCtrl) begin
			pressurized <= 0;
			evacuating <= 1;
		end
		
		if(evacuating & eDone) begin
			evacuated <= 1;
			evacuating <= 0;
		end
	end
	
	always @(posedge rst) begin
		pressurizing <= 0;
		pressurized <= 0;
	end
	
	
	always @(posedge rst) begin
		pressurized <= 0;
		evacuated <= 1;
		pressurizing <= 0;
		evacuating <= 0;
	end
endmodule

assignment_2/iVerilog/Chamber_Test.v
`include "Timer.v"
`include "Chamber.v"

module testBench;
	wire clk, rst;
	wire pressurizeCtrl, evacuateCtrl;
	wire pressurized, evacuated;

	Chamber c(clk, rst, pressurizeCtrl, evacuateCtrl, pressurized, evacuated);
	Tester aTester(clk, rst, pressurizeCtrl, evacuateCtrl, pressurized, evacuated);

	// file for gtkwave
	initial begin
		// these two files support gtkwave and are required
		$dumpfile("chamber.vcd");
		$dumpvars(1, c);
	end
endmodule

module Tester (clk, rst, pressurizeCtrl, evacuateCtrl, pressurized, evacuated);
 input pressurized, evacuated;
 output clk, rst;
 output pressurizeCtrl, evacuateCtrl;
 
 reg clk, rst;
 reg pressurizeCtrl, evacuateCtrl;
 parameter stimDelay = 20;

 initial // Response
 begin
 $display("\t\t clk rst \t pressurized \t Time ");
 $monitor("\t\t %b\t %b \t %b", clk, rst, pressurized, $time );
 end

 initial // Stimulus
 begin
 clk = 0; rst = 0; pressurizeCtrl = 0; evacuateCtrl = 0;
 
 rst = 1;
 clk = 0; #stimDelay clk = 1; #stimDelay
 
 rst = 0;
 pressurizeCtrl = 1;
 clk = 0; #stimDelay clk = 1; #stimDelay
 pressurizeCtrl = 0;
 
 clk = 0; #stimDelay clk = 1; #stimDelay
 clk = 0; #stimDelay clk = 1; #stimDelay
 clk = 0; #stimDelay clk = 1; #stimDelay
 clk = 0; #stimDelay clk = 1; #stimDelay
 clk = 0; #stimDelay clk = 1; #stimDelay
 clk = 0; #stimDelay clk = 1; #stimDelay
 clk = 0; #stimDelay clk = 1; #stimDelay
 clk = 0; #stimDelay clk = 1; #stimDelay
 clk = 0; #stimDelay clk = 1; #stimDelay
 
 evacuateCtrl = 1;
 clk = 0; #stimDelay clk = 1; #stimDelay
 evacuateCtrl = 0;
 
 clk = 0; #stimDelay clk = 1; #stimDelay
 clk = 0; #stimDelay clk = 1; #stimDelay
 clk = 0; #stimDelay clk = 1; #stimDelay
 clk = 0; #stimDelay clk = 1; #stimDelay
 clk = 0; #stimDelay clk = 1; #stimDelay
 clk = 0; #stimDelay clk = 1; #stimDelay
 clk = 0; #stimDelay clk = 1; #stimDelay
 clk = 0; #stimDelay clk = 1; #stimDelay
 clk = 0; #stimDelay clk = 1; #stimDelay

 #(2*stimDelay); // needed to see END of simulation
 $finish; // finish simulation
 end
endmodule

assignment_2/iVerilog/chamber.vcd
$date
	Thu Jan 28 22:38:01 2016
$end
$version
	Icarus Verilog
$end
$timescale
	1s
$end
$scope module testBench $end
$scope module c $end
$var wire 1 ! clk $end
$var wire 1 " evacuateCtrl $end
$var wire 1 # pressurizeCtrl $end
$var wire 1 $ rst $end
$var wire 1 % pDone $end
$var wire 1 & eDone $end
$var reg 1 ' evacuated $end
$var reg 1 ( evacuating $end
$var reg 1 ) pressurized $end
$var reg 1 * pressurizing $end
$upscope $end
$upscope $end
$enddefinitions $end
#0
$dumpvars
0*
0)
0(
1'
0&
0%
1$
0#
0"
0!
$end
#20
1!
#40
0!
1#
0$
#60
1*
0'
1!
#80
0!
0#
#100
1!
#120
0!
#140
1!
#160
0!
#180
1!
#200
0!
#220
1&
1!
#240
0!
#260
1!
#280
0!
#300
1%
1!
#320
0!
#340
0*
1)
1!
#360
0!
#380
1!
#400
0!
#420
1!
#440
0!
1"
#460
0&
1(
0)
1!
#480
0!
0"
#500
1!
#520
0!
#540
1!
#560
0!
#580
1!
#600
0!
#620
1!
#640
0!
#660
1!
#680
0!
#700
1&
1!
#720
0!
#740
0(
1'
1!
