assignment_2/iVerilog/Timer.v
module Timer(clk, rst, stopVal, done);
	input clk, rst;
	input [0:2] stopVal;
	output reg done;
	
	reg [0:2] q;
	
	always @(*) begin
		done <= (q == stopVal);
	end
	
	always @(posedge clk) begin
		if(rst)
			q <= 3'b000;
		else begin
			if(q != stopVal)
				q <= q + 1;
			else
				q <= q;
		end
	end

endmodule

assignment_2/iVerilog/Departing.v
`include "Timer.v"

module Departing(clk, rst, departCtrl, arriving, departing, innerDoor, outerDoor, pressurized, evacuated);
	input clk, rst;
	input departCtrl, arriving, innerDoor, outerDoor, pressurized, evacuated;
	output reg departing;
	
	parameter reset = 3'b000;
	parameter min5 = 3'b001;
	parameter pres = 3'b010;
	parameter openOut = 3'b011;
	parameter evac = 3'b100;
	
	reg [3:0] ps = reset;
	reg [3:0] ns = reset;
	
	Timer t(clk, departCtrl, 3'b101, done);
	
	always @(*) 
		case(ps)
			reset: if(departCtrl) begin 
				ns = min5;
				end
			else begin 
				ns = reset;
				departing = 0;
				end
			
			min5: begin
				departing = 1;
				if(done) ns = pres;
				else if(rst) ns = reset;
				else ns = min5;
			end
			
			pres: if(pressurized) ns = openOut;
			else if(rst) ns = reset;
			else ns = pres;
			
			openOut: if(outerDoor) ns = evac;
			else if(rst) ns = reset;
			else ns = openOut;
			
			evac: if(evacuated) ns = reset;
			else if(rst) ns = reset;
			else ns = evac;
			
			default ns = ps;
	endcase
	
	always@(posedge clk) begin
		if(rst) begin
			ps <= reset;
		end begin
			ps <= ns;
		end
	end
endmodule

assignment_2/iVerilog/Departing_Test.v
// counter.v
`include "Departing.v"

module testBench;
	wire clk, rst;
	wire departCtrl;
	wire departing;
	wire arriving, innerDoor, outerDoor, pressurized, evacuated;

	Departing p(clk, rst, departCtrl, arriving, departing, innerDoor, outerDoor, pressurized, evacuated);
	Tester aTester(clk, rst, departCtrl, arriving, departing, innerDoor, outerDoor, pressurized, evacuated);

	// file for gtkwave
	initial begin
		// these two files support gtkwave and are required
		$dumpfile("departing.vcd");
		$dumpvars(1, p);
	end
endmodule

module Tester (clk, rst, departCtrl, arriving, departing, innerDoor, outerDoor, pressurized, evacuated);
 input departing;
 output clk, rst;
 output departCtrl, arriving, innerDoor, outerDoor, pressurized, evacuated;
 
 reg clk, rst;
 reg departCtrl, arriving, innerDoor, outerDoor, pressurized, evacuated;
 parameter stimDelay = 20;

 initial // Response
 begin
 $display("\t\t clk rst \t arriving \t Time ");
 $monitor("\t\t %b\t %b \t %b", clk, rst, departing, $time );
 end

 initial // Stimulus
 begin
 clk = 0; rst = 0; departCtrl = 0; arriving = 0; innerDoor = 0; outerDoor = 0; pressurized = 0; evacuated = 0;
 
 clk = 0; #stimDelay clk = 1; rst = 1; #stimDelay
 clk = 0; #stimDelay clk = 1; rst = 0; #stimDelay
 clk = 0; #stimDelay clk = 1; departCtrl = 1; #stimDelay
 
 clk = 0; #stimDelay clk = 1; departCtrl = 0; #stimDelay
 clk = 0; #stimDelay clk = 1; #stimDelay
 clk = 0; #stimDelay clk = 1; #stimDelay
 clk = 0; #stimDelay clk = 1; #stimDelay
 clk = 0; #stimDelay clk = 1; #stimDelay
 clk = 0; #stimDelay clk = 1; #stimDelay
 clk = 0; #stimDelay clk = 1; #stimDelay
 clk = 0; #stimDelay clk = 1; #stimDelay
 clk = 0; #stimDelay clk = 1; #stimDelay
 clk = 0; #stimDelay clk = 1; #stimDelay
 clk = 0; #stimDelay clk = 1; #stimDelay
 clk = 0; #stimDelay clk = 1; #stimDelay
 clk = 0; #stimDelay clk = 1; pressurized = 1; #stimDelay
 clk = 0; #stimDelay clk = 1; #stimDelay
 clk = 0; #stimDelay clk = 1; #stimDelay
 clk = 0; #stimDelay clk = 1; outerDoor = 1; #stimDelay
 clk = 0; #stimDelay clk = 1; #stimDelay
 clk = 0; #stimDelay clk = 1; #stimDelay
 clk = 0; #stimDelay clk = 1; evacuated = 1; #stimDelay
 clk = 0; #stimDelay clk = 1; #stimDelay
 clk = 0; #stimDelay clk = 1; #stimDelay
 clk = 0; #stimDelay clk = 1; #stimDelay
 clk = 0; #stimDelay clk = 1; rst = 1; departCtrl = 0; arriving = 0; innerDoor = 0; outerDoor = 0; pressurized = 0; evacuated = 0; #stimDelay
 clk = 0; #stimDelay clk = 1; rst = 0; #stimDelay
 clk = 0; #stimDelay clk = 1; departCtrl = 1; #stimDelay
 clk = 0; #stimDelay clk = 1; departCtrl = 0; #stimDelay
 clk = 0; #stimDelay clk = 1; #stimDelay
 clk = 0; #stimDelay clk = 1; #stimDelay
 clk = 0; #stimDelay clk = 1; #stimDelay
 clk = 0; #stimDelay clk = 1; #stimDelay
 clk = 0; #stimDelay clk = 1; #stimDelay
 clk = 0; #stimDelay clk = 1; #stimDelay
 clk = 0; #stimDelay clk = 1; pressurized = 1; #stimDelay
 clk = 0; #stimDelay clk = 1; rst = 1; #stimDelay
 clk = 0; #stimDelay clk = 1; rst = 0; #stimDelay
 clk = 0; #stimDelay clk = 1; pressurized = 0; #stimDelay
 clk = 0; #stimDelay clk = 1; departCtrl = 1; #stimDelay
 clk = 0; #stimDelay clk = 1; departCtrl = 0; #stimDelay
 clk = 0; #stimDelay clk = 1; #stimDelay
 clk = 0; #stimDelay clk = 1; #stimDelay
 clk = 0; #stimDelay clk = 1; #stimDelay
 clk = 0; #stimDelay clk = 1; #stimDelay
 clk = 0; #stimDelay clk = 1; departCtrl = 1; #stimDelay
 clk = 0; #stimDelay clk = 1; departCtrl = 0; #stimDelay
 clk = 0; #stimDelay clk = 1; #stimDelay
 clk = 0; #stimDelay clk = 1; #stimDelay
 

 #(2*stimDelay); // needed to see END of simulation
 $finish; // finish simulation
 end
endmodule

assignment_2/iVerilog/departing.vcd
$date
	Sun Jan 24 16:08:43 2016
$end
$version
	Icarus Verilog
$end
$timescale
	1s
$end
$scope module testBench $end
$scope module p $end
$var wire 1 ! arriving $end
$var wire 1 " clk $end
$var wire 1 # departCtrl $end
$var wire 1 $ evacuated $end
$var wire 1 % innerDoor $end
$var wire 1 & outerDoor $end
$var wire 1 ' pressurized $end
$var wire 1 ( rst $end
$var wire 1 ) done $end
$var reg 1 * departing $end
$var reg 4 + ns [3:0] $end
$var reg 4 , ps [3:0] $end
$upscope $end
$upscope $end
$enddefinitions $end
#0
$dumpvars
b0 ,
b0 +
0*
0)
0(
0'
0&
0%
0$
0#
0"
0!
$end
#20
1(
1"
#40
0"
#60
0(
1"
#80
0"
#100
b1 +
1#
1"
#120
0"
#140
1*
b1 ,
b1 +
0#
1"
#160
0"
#180
1"
#200
0"
#220
1"
#240
0"
#260
1"
#280
0"
#300
b10 +
1)
1"
#320
0"
#340
b10 ,
1"
#360
0"
#380
1"
#400
0"
#420
1"
#440
0"
#460
1"
#480
0"
#500
1"
#520
0"
#540
1"
#560
0"
#580
1"
#600
0"
#620
b11 +
1'
1"
#640
0"
#660
b11 ,
1"
#680
0"
#700
1"
#720
0"
#740
b100 +
1&
1"
#760
0"
#780
b100 ,
1"
#800
0"
#820
1"
#840
0"
#860
b0 +
1$
1"
#880
0"
#900
0*
b0 ,
1"
#920
0"
#940
1"
#960
0"
#980
1"
#1000
0"
#1020
0$
0'
0&
1(
1"
#1040
0"
#1060
0(
1"
#1080
0"
#1100
0)
b1 +
1#
1"
#1120
0"
#1140
1*
b1 ,
b1 +
0#
1"
#1160
0"
#1180
1"
#1200
0"
#1220
1"
#1240
0"
#1260
1"
#1280
0"
#1300
b10 +
1)
1"
#1320
0"
#1340
b10 ,
1"
#1360
0"
#1380
1"
#1400
0"
#1420
b11 +
1'
1"
#1440
0"
#1460
b0 +
b11 ,
1(
1"
#1480
0"
#1500
0*
b0 ,
b0 +
0(
1"
#1520
0"
#1540
0'
1"
#1560
0"
#1580
0)
b1 +
1#
1"
#1600
0"
#1620
1*
b1 ,
b1 +
0#
1"
#1640
0"
#1660
1"
#1680
0"
#1700
1"
#1720
0"
#1740
1"
#1760
0"
#1780
b10 +
1)
1"
#1800
0"
#1820
0)
b10 ,
1#
1"
#1840
0"
#1860
0#
1"
