assignment_1/counter_2/quartas_gate/DFlipFlop.sv
module DFlipFlop(q, qBar, D, clk, rst);
	input D, clk, rst;
	output q, qBar;
	reg q;
	not n1 (qBar, q);
		always@ (negedge rst or posedge clk) begin
			if(!rst)
				q = 0;
			else
				q = D;
end endmodule

assignment_1/iverilog/counterOne.v
module CounterOne(q, clk, rst);
	input clk, rst;
	output [0:3] q;
	output test;
	
	wire [0:3] qBar;
	
	//module DFlipFlop(q, qBar, D, clk, rst);
	DFlipFlop c0 (q[3], qBar[3], qBar[3], clk, rst);
	DFlipFlop c1 (q[2], qBar[2], qBar[2], q[3], rst);
	DFlipFlop c2 (q[1], qBar[1], qBar[1], q[2], rst);
	DFlipFlop c3 (q[0], qBar[0], qBar[0], q[1], rst);
endmodule

assignment_1/iverilog/counterOneTop.v
// counter.v
`include "DFlipFlop.v"
`include "counterOne.v"

module testBench;
 wire [0:3] q;
 wire clk, rst;
 
 CounterOne counter(q, clk, rst);
 Tester aTester(q, clk, rst);
 
 // file for gtkwave
 initial
 begin
 // these two files support gtkwave and are required
 $dumpfile("counterOne0.vcd");
 $dumpvars(1, counter);
 end
endmodule

module Tester (q, clk, reset);

 input [3:0] q;
 output clk, rst;
 reg clk, rst;
 parameter stimDelay = 20;

 initial // Response
 begin
 $display("\t\t clk rst \t q \t Time ");
 $monitor("\t\t %b\t %b \t %b \t %b", clk, rst, q, $time );
 end

 initial // Stimulus
 begin
 clk = 0; rst = 0;
 #stimDelay clk = 1;
 #stimDelay clk = 0;
 #stimDelay clk = 1;
 #stimDelay clk = 0;
 #stimDelay clk = 1;
 #stimDelay clk = 0;
 #stimDelay clk = 1;

 #(2*stimDelay); // needed to see END of simulation
 $finish; // finish simulation
 end
endmodule

assignment_1/iverilog/counterOne0.vcd
$date
	Thu Jan 07 15:43:47 2016
$end
$version
	Icarus Verilog
$end
$timescale
	1s
$end
$scope module testBench $end
$scope module counter $end
$var wire 1 ! clk $end
$var wire 4 " q [3:0] $end
$var wire 4 # qBar [3:0] $end
$var wire 1 $ rst $end
$var wire 1 % test $end
$upscope $end
$upscope $end
$enddefinitions $end
#0
$dumpvars
z%
0$
b1111 #
b0 "
0!
$end
#20
b0 #
b1111 "
1$
1!
#40
0!
#60
b1 #
b1110 "
1!
#80
0!
#100
b10 #
b1101 "
1!
#120
0!
#140
b11 #
b1100 "
1!
#160
0!
#180
b100 #
b1011 "
1!
#200
0!
#220
b101 #
b1010 "
1!
#240
0!
#260
b110 #
b1001 "
1!
#280
0!
#300
b111 #
b1000 "
1!
#320
0!
#340
b1000 #
b111 "
1!
#360
0!
#380
b1001 #
b110 "
1!
#400
0!
#420
b1010 #
b101 "
1!
#440
0!
#460
b1011 #
b100 "
1!
#480
0!
#500
b1100 #
b11 "
1!
#520
0!
#540
b1101 #
b10 "
1!
#560
0!
#580
b1110 #
b1 "
1!
#600
0!
#620
b1111 #
b0 "
1!
#640
0!
#660
b0 #
b1111 "
1!
