assignment_1/counter_2/quartas_gate/DFlipFlop.sv
module DFlipFlop(q, qBar, D, clk, rst);
	input D, clk, rst;
	output q, qBar;
	reg q;
	not n1 (qBar, q);
		always@ (negedge rst or posedge clk) begin
			if(!rst)
				q = 0;
			else
				q = D;
end endmodule

assignment_1/iverilog/counterOne.v
module CounterOne(q, clk, rst);
	input clk, rst;
	output [0:3] q;
	output test;
	
	wire [0:3] qBar;
	
	//module DFlipFlop(q, qBar, D, clk, rst);
	DFlipFlop c0 (q[3], qBar[3], qBar[3], clk, rst);
	DFlipFlop c1 (q[2], qBar[2], qBar[2], q[3], rst);
	DFlipFlop c2 (q[1], qBar[1], qBar[1], q[2], rst);
	DFlipFlop c3 (q[0], qBar[0], qBar[0], q[1], rst);
endmodule

assignment_1/iverilog/counterOneTop.v
// counter.v
`include "DFlipFlop.v"
`include "counterOne.v"

module testBench;
 wire [0:3] q;
 wire clk, rst;
 
 CounterOne counter(q, clk, rst);
 Tester aTester(q, clk, rst);
 
 // file for gtkwave
 initial
 begin
 // these two files support gtkwave and are required
 $dumpfile("counterOne0.vcd");
 $dumpvars(1, counter);
 end
endmodule

module Tester (q, clk, rst);

 input [3:0] q;
 output clk, rst;
 reg clk, rst;
 parameter stimDelay = 20;

 initial // Response
 begin
 $display("\t\t clk rst \t q \t Time ");
 $monitor("\t\t %b\t %b \t %b", clk, rst, q, $time );
 end

 initial // Stimulus
 begin
 clk = 0; rst = 0;
 #stimDelay clk = 1; rst = 1;
 #stimDelay clk = 0;
 #stimDelay clk = 1;
 #stimDelay clk = 0;
 #stimDelay clk = 1;
 #stimDelay clk = 0;
 #stimDelay clk = 1;
 #stimDelay clk = 0;
 #stimDelay clk = 1;
 #stimDelay clk = 0;
 #stimDelay clk = 1;
 #stimDelay clk = 0;
 #stimDelay clk = 1;
 #stimDelay clk = 0;
 #stimDelay clk = 1;

 #(2*stimDelay); // needed to see END of simulation
 $finish; // finish simulation
 end
endmodule

assignment_1/iverilog/counterOne0.vcd
$date
	Thu Jan 07 14:49:20 2016
$end
$version
	Icarus Verilog
$end
$timescale
	1s
$end
$scope module testBench $end
$scope module counter $end
$var wire 1 ! clk $end
$var wire 4 " q [0:3] $end
$var wire 4 # qBar [0:3] $end
$var wire 1 $ rst $end
$var wire 1 % test $end
$upscope $end
$upscope $end
$enddefinitions $end
#0
$dumpvars
0%
0$
b1111 #
b0 "
0!
$end
#20
b0 #
1%
b1111 "
1$
1!
#40
0!
#60
b1000 #
0%
b111 "
1!
#80
0!
#100
b100 #
1%
b1011 "
1!
#120
0!
#140
b1100 #
0%
b11 "
1!
#160
0!
#180
b10 #
1%
b1101 "
1!
#200
0!
#220
b1010 #
0%
b101 "
1!
#240
0!
#260
b110 #
1%
b1001 "
1!
#280
0!
#300
b1110 #
0%
b1 "
1!
