assignment_1/counter_2/iverilog/counterTwo.v
module CounterTwo(q, clk, rst);
	input clk, rst;
	output [3:0] q;
	
	reg [3:0] ps;
	reg [3:0] ns;

	always @(*)
		begin
			ns[0] <= ~ps[0];
			ns[1] <= ps[0] ~^ ps[1];
			ns[2] <= (~ps[0] & ~ps[1] & ~ps[2]) | (ps[2] & ps[0]) | (ps[2] & ps[1]);
			ns[3] <= (ps[3] & ps[2]) | (ps[3] & ps[1]) | (ps[3] & ps[0]) | (~ps[0] & ~ps[1] & ~ps[2] & ~ps[3]);
		end
		
	assign q = ps;	
	always @(negedge rst or posedge clk)
		begin
			if(!rst)
				begin
					ps <= 0;
				end
			else
				begin
					ps <= ns;
				end
		end
	
	
endmodule

assignment_1/counter_2/iverilog/counterTwoTop.v
// counter.v
`include "DFlipFlop.v"
`include "counterTwo.v"

module testBench;
 wire [3:0] q;
 wire clk, rst;
 
 CounterTwo counter(q, clk, rst);
 Tester aTester(q, clk, rst);
 
 // file for gtkwave
 initial
 begin
 // these two files support gtkwave and are required
 $dumpfile("counterTwo0.vcd");
 $dumpvars(1, counter);
 end
endmodule

module Tester (q, clk, rst);

 input [3:0] q;
 output clk, rst;
 reg clk, rst;
 parameter stimDelay = 20;

 integer i;

 initial // Response
 begin
 $display("\t\t clk rst \t q \t Time ");
 $monitor("\t\t %b\t %b \t %b", clk, rst, q, $time );
 end

 initial // Stimulus
 begin
 clk = 0; rst = 0;
 #stimDelay clk = 1; rst = 1;
 
 for (i = 0; i < 16; i = i +1) begin
	#stimDelay clk = 0;
	#stimDelay clk = 1;
 end

 #(2*stimDelay); // needed to see END of simulation
 $finish; // finish simulation
 end
endmodule

assignment_1/counter_2/iverilog/counterTwo0.vcd
$date
	Thu Jan 07 22:12:54 2016
$end
$version
	Icarus Verilog
$end
$timescale
	1s
$end
$scope module testBench $end
$scope module counter $end
$var wire 1 ! clk $end
$var wire 4 " q [3:0] $end
$var wire 1 # rst $end
$var reg 4 $ ns [3:0] $end
$var reg 4 % ps [3:0] $end
$upscope $end
$upscope $end
$enddefinitions $end
#0
$dumpvars
b0 %
b1111 $
0#
b0 "
0!
$end
#20
b1110 $
b1111 %
b1111 "
1#
1!
#40
0!
#60
b1101 $
b1110 %
b1110 "
1!
#80
0!
#100
b1100 $
b1101 %
b1101 "
1!
#120
0!
#140
b1011 $
b1100 %
b1100 "
1!
#160
0!
#180
b1010 $
b1011 %
b1011 "
1!
#200
0!
#220
b1001 $
b1010 %
b1010 "
1!
#240
0!
#260
b1000 $
b1001 %
b1001 "
1!
#280
0!
#300
b111 $
b1000 %
b1000 "
1!
#320
0!
#340
b110 $
b111 %
b111 "
1!
#360
0!
#380
b101 $
b110 %
b110 "
1!
#400
0!
#420
b100 $
b101 %
b101 "
1!
#440
0!
#460
b11 $
b100 %
b100 "
1!
#480
0!
#500
b10 $
b11 %
b11 "
1!
#520
0!
#540
b1 $
b10 %
b10 "
1!
#560
0!
#580
b0 $
b1 %
b1 "
1!
#600
0!
#620
b1111 $
b0 %
b0 "
1!
#640
0!
#660
b1110 $
b1111 %
b1111 "
1!
